{"index.md":"cba298bc","leaddoc_antdesignvue.md":"b5eaec76","leaddoc_githubsynstogitee.md":"92c209b6","leaddoc_knt健康平台技术文档.md":"34d43b93","leaddoc_knt微前端.md":"02388b71","leaddoc_linux.md":"e5a26d79","leaddoc_macos.md":"0d10b7df","leaddoc_nginx.md":"ec584226","leaddoc_prettier.md":"313cf58b","leaddoc_python.md":"921ba158","leaddoc_quickwebserve.md":"4b35fafd","leaddoc_tarovsuni-app选型对比.md":"750b99aa","leaddoc_typescript.md":"ef8d10dc","leaddoc_vbenadmin.md":"67c29ce0","leaddoc_yargs入门.md":"d8147790","leaddoc_changeset.md":"f9c401e8","leaddoc_utils_dateutil.md":"8cff0922","leaddoc_utils_is.md":"722a895b","leaddoc_utils_utils.md":"5f923f54","leaddoc_utils_正则表达式.md":"22cfe97a","leaddoc_yalc.md":"11947d1f","leaddoc_技巧git.md":"9730b63e","leaddoc_提交规范git.md":"e7bc47f4","noah_knt_互医项目.md":"11279089","noah_knt_运维.md":"48c94ac8","noah_utils_常用工具.md":"adcf6b50","pages_前端技术栈.md":"d3ef7e4f","rear_index.md":"e9b30528"}
